influential/__init__.py
influential/centrality.py
influential/exir.py
influential/ranNorm.py
influential/rank.py
influential/sir.py
influential/stats.py
influential/visualize.py
influential/test/__init__.py
influential-0.0.22.dist-info/METADATA
influential-0.0.22.dist-info/WHEEL
influential-0.0.22.dist-info/top_level.txt
influential-0.0.22.dist-info/RECORD
