Metadata-Version: 2.1
Name: influential
Version: 0.0.22
Summary: Identification and Classification of the Most Influential Nodes
Home-page: http://pypi.python.org/pypi/influential/
Author: Adrian Salavaty
Author-email: abbas.salavaty@gmail.com
License: GPL-3
Keywords: influential
Platform: UNKNOWN
Classifier: Development Status :: 5 - Production/Stable
Classifier: Intended Audience :: Science/Research
Classifier: License :: OSI Approved :: GNU General Public License v3 (GPLv3)
Classifier: Programming Language :: Python :: 3
Requires-Dist: igraph
Requires-Dist: pandas
Requires-Dist: numpy
Requires-Dist: statistics
Requires-Dist: statsmodels
Requires-Dist: scipy
Requires-Dist: plotnine
Requires-Dist: tqdm
Requires-Dist: scikit-learn
